<annotation>
  <folder>VOC2007</folder>
  <filename>000036_1.jpg</filename>
  <size>
    <width>1480</width>
    <height>1010</height>
    <depth>3</depth>
  </size>
  <object>
    <name>grape</name>
    <difficult>0</difficult>
    <bndbox>
      <xmin>197.573296489673</xmin>
      <ymin>768.3628782820696</ymin>
      <xmax>306.573296489673</xmax>
      <ymax>905.3628782820696</ymax>
    </bndbox>
  </object>
  <object>
    <name>grape</name>
    <difficult>0</difficult>
    <bndbox>
      <xmin>358.573296489673</xmin>
      <ymin>721.3628782820696</ymin>
      <xmax>450.573296489673</xmax>
      <ymax>826.3628782820696</ymax>
    </bndbox>
  </object>
  <object>
    <name>grape</name>
    <difficult>0</difficult>
    <bndbox>
      <xmin>329.573296489673</xmin>
      <ymin>12.362878282069623</ymin>
      <xmax>418.573296489673</xmax>
      <ymax>104.36287828206962</ymax>
    </bndbox>
  </object>
  <object>
    <name>grape</name>
    <difficult>0</difficult>
    <bndbox>
      <xmin>242.573296489673</xmin>
      <ymin>33.36287828206962</ymin>
      <xmax>302.573296489673</xmax>
      <ymax>97.36287828206962</ymax>
    </bndbox>
  </object>
  <object>
    <name>grape</name>
    <difficult>0</difficult>
    <bndbox>
      <xmin>799.573296489673</xmin>
      <ymin>613.3628782820696</ymin>
      <xmax>853.573296489673</xmax>
      <ymax>690.3628782820696</ymax>
    </bndbox>
  </object>
  <object>
    <name>grape</name>
    <difficult>0</difficult>
    <bndbox>
      <xmin>858.573296489673</xmin>
      <ymin>635.3628782820696</ymin>
      <xmax>896.573296489673</xmax>
      <ymax>687.3628782820696</ymax>
    </bndbox>
  </object>
  <object>
    <name>grape</name>
    <difficult>0</difficult>
    <bndbox>
      <xmin>1025.5732964896729</xmin>
      <ymin>607.3628782820696</ymin>
      <xmax>1056.5732964896729</xmax>
      <ymax>657.3628782820696</ymax>
    </bndbox>
  </object>
  <object>
    <name>grape</name>
    <difficult>0</difficult>
    <bndbox>
      <xmin>608.573296489673</xmin>
      <ymin>601.3628782820696</ymin>
      <xmax>652.573296489673</xmax>
      <ymax>681.3628782820696</ymax>
    </bndbox>
  </object>
  <object>
    <name>grape</name>
    <difficult>0</difficult>
    <bndbox>
      <xmin>877.573296489673</xmin>
      <ymin>287.36287828206963</ymin>
      <xmax>916.573296489673</xmax>
      <ymax>360.36287828206963</ymax>
    </bndbox>
  </object>
  <object>
    <name>grape</name>
    <difficult>0</difficult>
    <bndbox>
      <xmin>1002.573296489673</xmin>
      <ymin>252.36287828206963</ymin>
      <xmax>1041.5732964896729</xmax>
      <ymax>313.36287828206963</ymax>
    </bndbox>
  </object>
  <object>
    <name>grape</name>
    <difficult>0</difficult>
    <bndbox>
      <xmin>918.573296489673</xmin>
      <ymin>137.36287828206963</ymin>
      <xmax>956.573296489673</xmax>
      <ymax>198.36287828206963</ymax>
    </bndbox>
  </object>
  <object>
    <name>grape</name>
    <difficult>0</difficult>
    <bndbox>
      <xmin>809.573296489673</xmin>
      <ymin>47.36287828206962</ymin>
      <xmax>853.573296489673</xmax>
      <ymax>116.36287828206962</ymax>
    </bndbox>
  </object>
  <object>
    <name>grape</name>
    <difficult>0</difficult>
    <bndbox>
      <xmin>638.573296489673</xmin>
      <ymin>110.36287828206962</ymin>
      <xmax>681.573296489673</xmax>
      <ymax>173.36287828206963</ymax>
    </bndbox>
  </object>
  <object>
    <name>grape</name>
    <difficult>0</difficult>
    <bndbox>
      <xmin>656.573296489673</xmin>
      <ymin>44.36287828206962</ymin>
      <xmax>711.573296489673</xmax>
      <ymax>133.36287828206963</ymax>
    </bndbox>
  </object>
  <object>
    <name>grape</name>
    <difficult>0</difficult>
    <bndbox>
      <xmin>175.573296489673</xmin>
      <ymin>506.36287828206963</ymin>
      <xmax>210.573296489673</xmax>
      <ymax>566.3628782820696</ymax>
    </bndbox>
  </object>
</annotation>
